<?xml version="1.0" encoding="utf-8" ?>
<LanguageData>

  <!--=========== Main menu ==========-->
  <Tutorial>Öğretici</Tutorial>
  <NewColony>Yeni Koloni</NewColony>
  <BackToGame>Oyuna Geri Dön</BackToGame>
  <ReviewScenario>Senaryoyu incele</ReviewScenario>
  <Save>Kaydet</Save>
  <LoadGame>Oyunu Yükle</LoadGame>
  <Options>Ayarlar</Options>
  <Mods>Modlar</Mods>
  <Credits>Jenerik</Credits>
  <QuitToMainMenu>Ana Menüye dön</QuitToMainMenu>
  <SaveAndQuitToMainMenu>Kaydet ve ana menüye dön</SaveAndQuitToMainMenu>
  <QuitToOS>Oyundan Çık</QuitToOS>
  <SaveAndQuitToOS>Kaydet ve masaüstüne dön</SaveAndQuitToOS>
  <FictionPrimer>El Kitabı</FictionPrimer>
  <LudeonBlog>Ludeon bloğu</LudeonBlog>
  <Forums>Forumlar</Forums>
  <OfficialWiki>Resmi wiki</OfficialWiki>
  <TynansTwitter>Tynan'ın twitterı</TynansTwitter>
  <TynansDesignBook>Tynan's tasarım kitabı</TynansDesignBook>
  <HelpTranslate>RimWorld'ü çevirmeye yardım et</HelpTranslate>
  <BuySoundtrack>Ses Dosyası Satın Al</BuySoundtrack>
  <CreateWorld>Dünya Oluştur</CreateWorld>
  
  <!--=========== Create/review world ================-->
  <ReviewWorld>Dünyayı Gözden Geçir</ReviewWorld>
  <WorldGenerate>Oluştur</WorldGenerate>
  <WorldSaveAndFinish>Bitir</WorldSaveAndFinish>
  <Reset>Reset</Reset>
  <WorldSize>Boyut</WorldSize>
  <WorldSeed>Seed</WorldSeed>
  <RandomizeSeed>Rastgele Seed</RandomizeSeed>

  <!--=========== Select world ===================-->
  <SelectWorld>Dünya Seç</SelectWorld>
  <WorldChooseButton>Seç</WorldChooseButton>
  <NoWorldsFilesFound>Dünya dosyası bulunamadı. Önce bir dünya yarat.</NoWorldsFilesFound>
  
  <!--=========== Version info ==========-->
  <BuildNowAvailable>Yapı {0} artık kullanılabilir. Daha fazla bilgi için: ludeon.com</BuildNowAvailable>
	<BuildUpToDate>Yapı güncel.</BuildUpToDate>
	<ErrorGettingVersionInfo>Versiyon bilgisi alırken hata: {0}</ErrorGettingVersionInfo>
	<LoadingVersionInfo>Versiyon bilgisi yükleniyor...</LoadingVersionInfo>

  <!--=========== World generator =========-->
  <GenerateWorld>Dünya Oluştur</GenerateWorld>

  <!--=========== Mods screen ==========-->
  <OpenSteamWorkshop>Steam Atölyesini Aç</OpenSteamWorkshop>
  <GetModsFromForum>Get mods from forum</GetModsFromForum>
  <OpenModsDataFolder>Mod Dosyasını Aç</OpenModsDataFolder>
  <ConfirmDisableCoreMod>Are you sure you want to disable the core mod? The game won't work at all unless you have another mod that replaces all the core functionality.\n\nRemember, other mods can override defs in the core mod by using the same defName.</ConfirmDisableCoreMod>
  <ConfirmDeleteMod>Are you sure you want to delete all the content for {0}?</ConfirmDeleteMod>
  <Unsubscribe>Unsubscribe</Unsubscribe>
  <ConfirmUnsubscribe>Are you sure you want to unsubscribe from {0}?</ConfirmUnsubscribe>
  <Author>Author</Author>
  <WorkshopPage>Workshop page</WorkshopPage>
  <UploadToSteamWorkshop>Upload to Steam Workshop</UploadToSteamWorkshop>
  <UpdateOnSteamWorkshop>Update on Steam Workshop</UpdateOnSteamWorkshop>
  <UploadAlreadyInProgress>Upload already in progress.</UploadAlreadyInProgress>
  <WorkshopSubmissionFailed>Workshop submission failed.\n\nReason: {0}</WorkshopSubmissionFailed>
  <WorkshopUploadSucceeded>Successfully uploaded {0}.</WorkshopUploadSucceeded>
  <Downloading>Downloading</Downloading>
  <Source>Source</Source>
  <ModTargetVersion>For version: {0}</ModTargetVersion>
  <ModNotMadeForThisVersion>This mod was not made for this version of RimWorld, and will probably not work correctly.</ModNotMadeForThisVersion>
  <MessageModNeedsWellFormattedTargetVersion>Mod needs a well-formatted target version in About.xml. Like this: &lt;targetVersion&gt;{0}&lt;/targetVersion&gt;.</MessageModNeedsWellFormattedTargetVersion>
  <DragToReorder>Drag to reorder</DragToReorder>

    <!--=========== Select scenario =============-->
  <ChooseScenario>Choose scenario</ChooseScenario>
  <ScenariosCustom>Custom</ScenariosCustom>
  <ScenariosSteamWorkshop>Steam Workshop</ScenariosSteamWorkshop>
  <ScenarioEditor>Scenario editor</ScenarioEditor>
  <Delete>Delete</Delete>
  
  <!--============ Scenario editor ===============-->
  <Seed>seed</Seed>
  <Load>Load</Load>
  <EditMode>edit mode</EditMode>
  <Summary>Summary</Summary>
  <AddPart>Add part</AddPart>
  <TextFieldsMustBeFilled>All text fields must be filled.</TextFieldsMustBeFilled>
  <ConfirmSteamWorkshopUpload>Are you sure you want to upload this to the Steam Workshop?\n\nYou must agree to the Steam Workshop terms of service. Find the full terms here:\n\nhttp://steamcommunity.com/sharedfiles/workshoplegalagreement</ConfirmSteamWorkshopUpload>
  <ConfirmContentAuthor>Obviously you should only upload content that you created yourself.\n\nDid you create this content yourself?</ConfirmContentAuthor>
  <Incompatible>Incompatible</Incompatible>
  <TooMany>Çok fazla (maks {0}): </TooMany>
  <CanBeUpdatedOnWorkshop>Can be updated on Workshop, since you are the author.</CanBeUpdatedOnWorkshop>

  <!--=========== Select storyteller ==========-->
  <ChooseAIStoryteller>Hikayeni anlatacak bir AI seç</ChooseAIStoryteller>
  <HowStorytellersWork>yapay zeka hikayecisi korsan saldırıları , kaynak düşmesi veya hayvan saldırıları gibi olaylar oluşturur.Onların seçimleri koloninin hikayesini etkiler.</HowStorytellersWork>
  <MustChooseDifficulty>Lütfen bir zorluk seç.</MustChooseDifficulty>
  <Difficulty>Zorluk</Difficulty>
  <MustChooseChallengeScale>Lütfen bir zorluk seç.</MustChooseChallengeScale>
  <ChallengeScale>Zorluk seviyesi</ChallengeScale>
  <ChallengeScaleTip>Hikayeyi anlatan AI sana tehditler yolladığında, {0} kadar daha büyük olucaklar.</ChallengeScaleTip>
  <ChallengeScale_BuilderMode>İnşaat modu</ChallengeScale_BuilderMode>
  <ChallengeScale_Casual>Orta</ChallengeScale_Casual>
  <ChallengeScale_Rough>Sert</ChallengeScale_Rough>
  <ChallengeScale_Challenge>Zorlu</ChallengeScale_Challenge>
  <ChallengeScale_SeriousChallegne>Çok zorlu</ChallengeScale_SeriousChallegne>
  <ChallengeScale_ExtremeChallenge>Aşırı zorlu</ChallengeScale_ExtremeChallenge>

  <!--=========== Landing site select =========-->
  <SelectLandingSite>Bir iniş alanı seç</SelectLandingSite>
  <SelectSite>Alan seç</SelectSite>
  <MustSelectLandingSite>Lütfen bir iniş alanı şeç</MustSelectLandingSite>
  <CannotLandBiome>Bu iklime iniş yapamazsın: {0}</CannotLandBiome>
  <WorldRenderMode>Modu</WorldRenderMode>
  <WorldRenderModeFull>Tam</WorldRenderModeFull>
  <WorldRenderModeTemperature>Isı</WorldRenderModeTemperature>
  <WorldRenderModeElevation>Yükseklik</WorldRenderModeElevation>
  <WorldRenderModeFertility>Bereket</WorldRenderModeFertility>
  <WorldRenderModeRainfall>Yağış miktarı</WorldRenderModeRainfall>
  <WorldRenderModeBiomes>İklim</WorldRenderModeBiomes>
  <BiomeNotImplemented>İklim henüz eklenmedi</BiomeNotImplemented>
  <Biome>İklim</Biome>
  <Terrain>Arazi</Terrain>
  <Elevation>Yükseklik</Elevation>
  <Fertility>Bereket</Fertility>
  <AvgTemp>Ortalama Sıcaklık</AvgTemp>
  <Rainfall>Yağış miktarı</Rainfall>
  <HasCoast0>Kuzey kıyısı</HasCoast0>
  <HasCoast1>Doğu kıyısı</HasCoast1>
  <HasCoast2>Güney kıyısı</HasCoast2>
  <HasCoast3>Batı kıyısı</HasCoast3>
  <FactionBase>Birlik merkzi</FactionBase>
  <StoneTypesHere>Kaya tipleri</StoneTypesHere>

  <!--=========== Character chooser ==========-->
  <CreateCharacters>Karakterler yarat</CreateCharacters>
  <FirstNameDesc>Karakterin ismi.\n\nBu sadece bazı menülerde gösterilir.</FirstNameDesc>
  <ShortIdentifierDesc>Karakterin kısa adı.\n\nBu her zaman gösterilir. İsim yada soyisim olabilir, yada tamamen başka bir nick olabilir.</ShortIdentifierDesc>
  <LastNameDesc>Karakterin soyadı.\n\nBu sadece bazı menülerde gösterilir.</LastNameDesc>
  <Randomize>Rastgele</Randomize>
  <AgeIndicator>Yaş {0}</AgeIndicator>
  <Backstory>Arkaplan</Backstory>
  <IncapableOf>Yapamadıkları</IncapableOf>
  <Traits>Özellikler</Traits>
  <TraitsDoNothing>Özellikler sadece eğlenceli hikaye parcalarıdır; çoğu hiçbir şey yapmaz. Bu ileriki sürümlerde değişicektir.</TraitsDoNothing>
  <Skills>Beceriler</Skills>
  <NoneLower>hiç</NoneLower>
  <Adulthood>Yetişkinlik</Adulthood>
  <Childhood>Çocukluğu</Childhood>
  <Male>Erkek</Male>
  <Female>Kadın</Female>
  <Pain>Acı</Pain>
  <Health>Sağlık</Health>
  <Relations>İlişkiler</Relations>

  <!--=========== Misc ==========-->
  <Start>Başlat</Start>
  <Advanced>Gelişmiş</Advanced>
  <Next>Sonraki</Next>
  <Back>Önceki</Back>
  
  <Gameplay>Oynanış</Gameplay>

  <ConfirmQuit>Çıkmak istediğine eminmisin? Kaydedilmemiş herşeyi kaybediceksin.</ConfirmQuit>
  
  <EveryoneNeedsValidName>Herkezin geçerli bir isime ihtiyacı var.</EveryoneNeedsValidName>

  <GeneratingWorld>Dünya yaratılıyor...</GeneratingWorld>
  <GeneratingMap>Harita yaratılıyor...</GeneratingMap>

</LanguageData>
