<?xml version="1.0" encoding="utf-8" ?>
<LanguageData>

  <!--================ General ================-->
  
	<Basics.label>Basis</Basics.label>
	<BasicsPawn.label>Basis</BasicsPawn.label>
	<BasicsNonPawn.label>Basis</BasicsNonPawn.label>
	
  <!--================ Non-pawn ================-->
  
	<Apparel.label>Kleidung</Apparel.label>
	<Weapon.label>Waffe</Weapon.label>
	<Building.label>Gebäude</Building.label>

  <!--=============== Virtual categories ==============-->
  
	<EquippedStatOffsets.label>Anpassung, wenn ausgerüstet</EquippedStatOffsets.label>
	<StuffStatFactors.label>Multiplikator, wenn etwas hieraus hergestellt ist</StuffStatFactors.label>
	<StuffStatOffsets.label>Offset, wenn etwas hieraus hergestellt ist</StuffStatOffsets.label>
	<StuffOfEquipmentStatFactors.label>Multiplikator, wenn Ausrüstung hieraus hergestellt ist</StuffOfEquipmentStatFactors.label>
	
  <!--================ Pawn ================-->
	
	<PawnCombat.label>Kampf</PawnCombat.label>
	<PawnSocial.label>Sozial</PawnSocial.label>
	<PawnMisc.label>Verschiedenes</PawnMisc.label>
	<PawnWork.label>Arbeit</PawnWork.label>
  
</LanguageData>
