<?xml version="1.0" encoding="utf-8" ?>
<LanguageData>
    
    <Human.label>İnsan</Human.label>
    <Human.description>A baseline human, mostly unmodified by gene engineering and mostly unchanged by evolutionary pressures on non-Earth planets.</Human.description>
    <Human_Leather.label>İnsan derisi</Human_Leather.label>
    <Human_Leather.description>İnsan derisi.</Human_Leather.description>
    <Human_Leather.stuffProps.stuffAdjective>İnsan derisi</Human_Leather.stuffProps.stuffAdjective>
    <Human_Meat.label>İnsan eti</Human_Meat.label>
    <Human_Meat.description>Çiğ insan eti.</Human_Meat.description>
    <Human_Corpse.label>İnsan cesedi</Human_Corpse.label>
    <Human_Corpse.description>Ölü birinin vücudu.</Human_Corpse.description>
    
</LanguageData>