<?xml version="1.0" encoding="UTF-8"?>
<LanguageData>
  
  <!-- EN: autobong -->
  <Autobong.label>Oto-Bong</Autobong.label>
  <!-- EN: An automatic smokeleaf-burning device which generates a smoke cloud around itself. Anyone in the cloud will become high on smokeleaf over time. -->
  <Autobong.description>Kendi etrafında bir duman bulutu oluşturan otomatik bir duman yaprağı yakan cihaz. Buluttaki herkes zamanla duman yaprağına boğulacak.</Autobong.description>
  
  <!-- EN: drum -->
  <Drum.label>davul</Drum.label>
  <!-- EN: A large wooden drum used as a music source for tribal rituals and parties. -->
  <Drum.description>Kabile ritüelleri ve partileri için müzik kaynağı olarak kullanılan büyük bir ahşap davul.</Drum.description>
  
  <!-- EN: dryad cocoon -->
  <DryadCocoon.label>orman perisi kozası</DryadCocoon.label>
  <!-- EN: A sphere of fibrous plant matter. A dryad inside is slowly morphing into a new form. Gauranlen trees grow these spheres to help protect the dryads as they morph. -->
  <DryadCocoon.description>Lifli bitki maddesinden oluşan bir küre. İçerideki bir orman perisi yavaş yavaş yeni bir forma dönüşüyor. Gauranlen ağaçları bu küreleri büyütürler ve bu küreler şekil değiştirirken dryadları korumaya yardımcı olur.</DryadCocoon.description>
  
  <!-- EN: dryad healing pod -->
  <DryadHealingPod.label>orman perisi şifa kapsülü</DryadHealingPod.label>
  <!-- EN: A sphere of fibrous plant matter. A dryad inside is slowly healing its wounds. -->
  <DryadHealingPod.description>Lifli bitki maddesinden oluşan bir küre. İçerideki bir Dryad yavaş yavaş yaralarını iyileştiriyor.</DryadHealingPod.description>
  
  <!-- EN: gaumaker pod -->
  <GaumakerCocoon.label>gauyapım kapsülü</GaumakerCocoon.label>
  <!-- EN: The result of the merging of several Gaumaker dryads, this symbiotic plant/animal pod is an essential part of the Gauranlen life cycle. After some time, it will flower into a mature Gauranlen pod which can be harvested to plant a new Gauranlen tree. -->
  <GaumakerCocoon.description>Birkaç Gauyapıcı orman perisi birleştirilmesinin sonucu olan bu simbiyotik bitki/hayvan bölmesi, Gauranlen yaşam döngüsünün önemli bir parçasıdır. Bir süre sonra, yeni bir Gauranlen ağacı dikmek için hasat edilebilecek olgun bir Gauranlen baklasına çiçek açacak.</GaumakerCocoon.description>
  
  <!-- EN: gibbet cage -->
  <GibbetCage.label>darağacı kafesi</GibbetCage.label>
  <!-- EN: A metal cage for holding and displaying corpses. This horrifying sight inspires terror and disgust in observers. It is an especially brutal and effective way to terrorize slaves. -->
  <GibbetCage.description>Cesetleri tutmak ve sergilemek için çelik bir kafes. Bu ürkütücü manzara, gözlemcilerde dehşet ve tiksinti uyandırıyor. Köleleri korkutmanın özellikle acımasız ve etkili bir yoludur.</GibbetCage.description>
  
  <!-- EN: kneel pillow -->
  <KneelPillow.label>minder</KneelPillow.label>
  <!-- EN: A pillow on which believers kneel while observing rituals, praying, or discussing. -->
  <KneelPillow.description>Ayinleri gözlemlerken, dua ederken veya tartışırken inananların diz çöktükleri bir yastık.</KneelPillow.description>
  
  <!-- EN: kneel sheet -->
  <KneelSheet.label>minder kılıf</KneelSheet.label>
  <!-- EN: A sheet on which believers kneel while observing rituals, praying, or discussing. -->
  <KneelSheet.description>Ritüelleri gözlemlerken, dua ederken veya tartışırken inananların diz çöktükleri bir çarşaf.</KneelSheet.description>
  
  <!-- EN: lectern -->
  <Lectern.label>kürsü</Lectern.label>
  <!-- EN: A slanted platform that holds a text in front of a speaker. Place it near the focus of rituals and speeches to extend the duration of their positive effects. -->
  <Lectern.description>Bir metni konuşmacının önünde tutan eğimli bir platform. Olumlu etkilerinin süresini uzatmak için onu ritüellerin ve konuşmaların odağına yakın bir yere yerleştirin.</Lectern.description>
  
  <!-- EN: lightball -->
  <LightBall.label>ışık topu</LightBall.label>
  <!-- EN: A decorative light that rotates and changes colors. Used as a focus for dance parties. -->
  <LightBall.description>Dönen ve renkleri değiştiren dekoratif bir ışık. Dans partileri için odak noktası olarak kullanılır.</LightBall.description>
  
  <!-- EN: loudspeaker -->
  <Loudspeaker.label>hoparlör</Loudspeaker.label>
  <!-- EN: A large loudspeaker for playing music. At least one is necessary to hold a dance party, and more loudspeakers will enhance the effect. -->
  <Loudspeaker.description>Müzik çalmak için büyük bir hoparlör. Bir dans partisi düzenlemek için en az bir tane gereklidir ve daha fazla hoparlör efekti artıracaktır.</Loudspeaker.description>
  
  <!-- EN: pew -->
  <Pew.label>uzun bank</Pew.label>
  <!-- EN: A long bench where ritual participants can sit while listening to a speaker. Place it facing rituals and speeches to extend the duration of their positive effects. -->
  <Pew.description>Bir konuşmacıyı dinlerken ritüel katılımcıların oturabileceği uzun bir bank. Olumlu etkilerinin süresini uzatmak için onu ritüellere ve konuşmalara yerleştirin.</Pew.description>
  
  <!-- EN: bonsai pot -->
  <PlantPot_Bonsai.label>bonsai saksısı</PlantPot_Bonsai.label>
  <!-- EN: This special pot is suitable for planting bonsai trees, which can improve the mood of people nearby and satisfy ideoligious requirements. -->
  <PlantPot_Bonsai.description>DBu özel saksı, yakınlardaki insanların ruh halini iyileştirebilecek ve ideolojik gereksinimleri karşılayabilecek bonsai ağaçları dikmek için uygundur.</PlantPot_Bonsai.description>
  
  <!-- EN: reliquary -->
  <Reliquary.label>kutsal sandık</Reliquary.label>
  <!-- EN: A ceremonial building that protects and displays a relic. Relics are ancient objects venerated by some cultures, belief systems, or religions. -->
  <Reliquary.description>Bir kalıntıyı koruyan ve sergileyen törensel bir bina. Kalıntılar, belirli bir ideolojiye inananlar tarafından saygı duyulan eski nesnelerdir.</Reliquary.description>
  
  <!-- EN: skullspike -->
  <Skullspike.label>Kafatası Çivi</Skullspike.label>
  <!-- EN: A spike mounted upright for the purpose of piercing and displaying a human skull. To some, displayed skulls are a symbol of power. To others, they represent barbaric evil. Skullspikes are an especially brutal and effective way to terrorize slaves. -->
  <Skullspike.description>Bir insan kafatasını delmek ve sergilemek amacıyla dik olarak monte edilmiş bir çivi. Bazıları için, görüntülenen kafatasları gücün bir simgesidir. Diğerleri için barbar kötülüğü temsil ederler. kafatası, köleleri korkutmanın özellikle acımasız ve etkili bir yoludur.</Skullspike.description>
  <!-- EN: skull of -->
  <Skullspike.comps.CompHasSources.inspectStringLabel>kafatası</Skullspike.comps.CompHasSources.inspectStringLabel>
  
  <!-- EN: slab bed -->
  <SlabBed.label>levha yatak</SlabBed.label>
  <!-- EN: A slab of hard material made to sleep on. Slab beds are uncomfortable, but some see their use as a demonstration of moral good. -->
  <SlabBed.description>Üzerinde uyumak için yapılmış sert bir malzeme levhası. Döşeme yatakları rahatsız edicidir, ancak bazıları kullanımlarını ahlaki iyiliğin bir göstergesi olarak görür.</SlabBed.description>
  
  <!-- EN: slab double bed -->
  <SlabDoubleBed.label>levha çift kişilik yatak</SlabDoubleBed.label>
  <!-- EN: A slab of hard material made to sleep on. Slab beds are uncomfortable, but some see their use as a demonstration of moral good. This one is wide enough to fit two people. -->
  <SlabDoubleBed.description>Üzerinde uyumak için yapılmış sert bir malzeme levhası. Döşeme yatakları rahatsız edicidir, ancak bazıları kullanımlarını ahlaki iyiliğin bir göstergesi olarak görür. Bu, iki kişinin sığabileceği kadar geniş.</SlabDoubleBed.description>
  
  <!-- EN: styling station -->
  <StylingStation.label>stil istasyonu</StylingStation.label>
  <!-- EN: A table with a mirror and styling tools. People can use this to change their look. -->
  <StylingStation.description>Aynalı ve şekillendirme aletleri olan bir masa. İnsanlar görünüşlerini değiştirmek için bunu kullanabilirler.</StylingStation.description>
  
</LanguageData>