<?xml version="1.0" encoding="UTF-8"?>
<LanguageData>
  
  <!-- EN: recent apostasy -->
  <ChangedIdeo_Know_Abhorrent.stages.recent_apostasy.label>son mürtet</ChangedIdeo_Know_Abhorrent.stages.recent_apostasy.label>
  
  <!-- EN: recent apostasy -->
  <ChangedIdeo_Know_Disapproved.stages.recent_apostasy.label>son mürtet</ChangedIdeo_Know_Disapproved.stages.recent_apostasy.label>
  
  <!-- EN: recent apostasy -->
  <ChangedIdeo_Know_Horrible.stages.recent_apostasy.label>son mürtet</ChangedIdeo_Know_Horrible.stages.recent_apostasy.label>
  
  <!-- EN: apostate -->
  <IsApostate_Abhorrent_Social.stages.apostate.label>mürted</IsApostate_Abhorrent_Social.stages.apostate.label>
  
  <!-- EN: apostate -->
  <IsApostate_Disapproved_Social.stages.apostate.label>mürted</IsApostate_Disapproved_Social.stages.apostate.label>
  
  <!-- EN: apostate -->
  <IsApostate_Horrible_Social.stages.apostate.label>mürted</IsApostate_Horrible_Social.stages.apostate.label>
  
</LanguageData>