<?xml version="1.0" encoding="UTF-8"?>
<LanguageData>

  <!-- EN: Vacuum exposure -->
  <AlertVacuumExposure>Vakuma maruz kalma</AlertVacuumExposure>
  <!-- EN: These people and animals are suffering from exposure to the vacuum of space:\n{0}\n\nGet them to a pressurized area before they die. -->
  <AlertVacuumExposureDesc>Bu insanlar ve hayvanlar, uzay vakumuna maruz kaldıkları için acı çekiyor:\n{0}\n\nOnları ölmeden önce basınçlı bir alana götür.</AlertVacuumExposureDesc>

  <!-- EN: Mechanoid threat -->
  <AlertMechanoidThreat>Mekanoit tehdidi</AlertMechanoidThreat>
  <!-- EN: A mechhive is conducting scans to determine your location. It will send a massive raid of hostile mechanoids when it locates you.\n\nFlee the map before mechanoids arrive! -->
  <AlertMechanoidThreatDesc>Bir mekakovan, konumunu belirlemek için taramalar yapıyor. Seni bulduğunda büyük bir düşman mekanoit grubu gönderecek.\n\nMekanoitler gelmeden haritadan kaçın!</AlertMechanoidThreatDesc>
  <!-- EN: Incoming mechanoids -->
  <AlertMechanoidThreatCritical>Yaklaşan mekanoitler</AlertMechanoidThreatCritical>
  <!-- EN: A mechhive has discovered your location. It will send multiple waves of hostile mechanoids.\n\nFlee the map before mechanoids arrive! -->
  <AlertMechanoidThreatCriticalDesc>Bir mekakovan konumunu tespit etti. Sen bu bölgeden kaçana kadar düşman mekanoitler göndermeye devam edecek.\n\nMekanoitler gelmeden haritadan kaç!</AlertMechanoidThreatCriticalDesc>

  <!-- Mechhive -->
  <!-- EN: Stabilizers remaining -->
  <StabilizersRemainingAlertLabel>Kalan dengeleyiciler</StabilizersRemainingAlertLabel>
  <!-- EN: The cerebrex core is currently invulnerable. Find and destroy its stabilizers to gain access to the core. -->
  <StabilizersRemainingAlertDescription>Serebreks çekirdeği şu anda yok edilemez. Çekirdeğe erişim sağlamak için dengeleyicilerini bulun ve yok et.</StabilizersRemainingAlertDescription>

  <!-- Relay -->
  <!-- EN: Stabilizers remaining -->
  <RelayStabilizersRemainingAlertLabel>Kalan dengeleyiciler</RelayStabilizersRemainingAlertLabel>
  <!-- EN: The relay is currently protected by nearby stabilizers. Destroy or hack them to destabilize it. -->
  <RelayStabilizersRemainingAlertDescription>Röle, şu anda yakınındaki dengeleyiciler tarafından korunuyor. Röleyi dengesiz hâle getirmek için dengeleyicileri yok et veya hackle.</RelayStabilizersRemainingAlertDescription>

  <!-- Scanner -->
  <!-- EN: Protect the scanner -->
  <SurveyScannerAlertLabel>Tarayıcıyı koru</SurveyScannerAlertLabel>
  <!-- EN: Protect the scanner until the surveying operation is complete. -->
  <SurveyScannerAlertDescription>Tarama işlemi tamamlanana kadar tarayıcıyı koru.</SurveyScannerAlertDescription>
  
</LanguageData>