<?xml version="1.0" encoding="UTF-8"?>
<LanguageData>
  
  <!-- EN: Bioferrite generator -->
  <BioferriteGenerator.stages.Bioferrite_generator.label>Biyoferrit jeneratörü</BioferriteGenerator.stages.Bioferrite_generator.label>
  <!-- EN: The buzz of that blasted machine will make me mad. It's like nails on a chalkboard. -->
  <BioferriteGenerator.stages.Bioferrite_generator.description>O lanet makinenin vızıltısı beni delirtecek. Karatahtaya sürtülen tırnaklar gibi.</BioferriteGenerator.stages.Bioferrite_generator.description>
  
  <!-- EN: blood rage -->
  <BloodRage.stages.blood_rage-0.label>kan öfkesi</BloodRage.stages.blood_rage-0.label>
  <!-- EN: blood rage -->
  <BloodRage.stages.blood_rage-1.label>kan öfkesi</BloodRage.stages.blood_rage-1.label>
  <!-- EN: I'm really angry. I feel like I could hit someone. -->
  <BloodRage.stages.blood_rage-1.description>Çok öfkeliyim. Elimden bir kaza çıkacak.</BloodRage.stages.blood_rage-1.description>
  <!-- EN: blood rage -->
  <BloodRage.stages.blood_rage-2.label>kan öfkesi</BloodRage.stages.blood_rage-2.label>
  <!-- EN: I want to hurt something. I want to hurt something so much. -->
  <BloodRage.stages.blood_rage-2.description>Bir şeyin canını yakmak istiyorum. Bir şeyin canını yakmayı çok istiyorum.</BloodRage.stages.blood_rage-2.description>
  <!-- EN: blood rage -->
  <BloodRage.stages.blood_rage-3.label>kan öfkesi</BloodRage.stages.blood_rage-3.label>
  <!-- EN: Smash everything into pieces! You all deserve it! -->
  <BloodRage.stages.blood_rage-3.description>Her şeyi paramparça et! Bunu hakettiniz!</BloodRage.stages.blood_rage-3.description>
  <!-- EN: blood rage -->
  <BloodRage.stages.blood_rage-4.label>kan öfkesi</BloodRage.stages.blood_rage-4.label>
  <!-- EN: I'll destroy you! I'll kill you! -->
  <BloodRage.stages.blood_rage-4.description>Sizi yok edeceğim! Sizi öldüreceğim!</BloodRage.stages.blood_rage-4.description>
  
  <!-- EN: cube sculpture -->
  <CubeSculptures.stages.cube_sculpture.label>küp heykeli</CubeSculptures.stages.cube_sculpture.label>
  <!-- EN: My sculpture... my beautiful sculpture! -->
  <CubeSculptures.stages.cube_sculpture.description>Heykelim... benim güzel heykelim!</CubeSculptures.stages.cube_sculpture.description>
  
  <!-- EN: cube withdrawal -->
  <CubeWithdrawl.stages.cube_withdrawal-0.label>küp mahrumiyeti</CubeWithdrawl.stages.cube_withdrawal-0.label>
  <!-- EN: I need to see the golden cube. Just once more. Please. -->
  <CubeWithdrawl.stages.cube_withdrawal-0.description>Altın küpü bir kez olsun görmeliyim. Sadece bir kez daha. Lütfen.</CubeWithdrawl.stages.cube_withdrawal-0.description>
  <!-- EN: cube withdrawal -->
  <CubeWithdrawl.stages.cube_withdrawal-1.label>küp mahrumiyeti</CubeWithdrawl.stages.cube_withdrawal-1.label>
  <!-- EN: Where's that cube? I miss it. I need it! -->
  <CubeWithdrawl.stages.cube_withdrawal-1.description>O küp nerede? Onu özledim. Ona ihtiyacım var!</CubeWithdrawl.stages.cube_withdrawal-1.description>
  <!-- EN: cube withdrawal -->
  <CubeWithdrawl.stages.cube_withdrawal-2.label>küp mahrumiyeti</CubeWithdrawl.stages.cube_withdrawal-2.label>
  <!-- EN: Where is my cube? Where is it? -->
  <CubeWithdrawl.stages.cube_withdrawal-2.description>Küpüm nerede? Nerede o?</CubeWithdrawl.stages.cube_withdrawal-2.description>
  
  <!-- EN: deadlife dust -->
  <DeadlifeDust.stages.deadlife_dust-0.label>ölüyaşam tozu</DeadlifeDust.stages.deadlife_dust-0.label>
  <!-- EN: This dust itches bad. -->
  <DeadlifeDust.stages.deadlife_dust-0.description>Bu toz çok kaşındırıyor.</DeadlifeDust.stages.deadlife_dust-0.description>
  <!-- EN: deadlife dust -->
  <DeadlifeDust.stages.deadlife_dust-1.label>ölüyaşam tozu</DeadlifeDust.stages.deadlife_dust-1.label>
  <!-- EN: I'm breaking out in rashes from this dust. It's burning my skin. -->
  <DeadlifeDust.stages.deadlife_dust-1.description>Bu toz yüzünden kurdeşen döküyorum. Cildimi yakıyor.</DeadlifeDust.stages.deadlife_dust-1.description>
  <!-- EN: deadlife dust -->
  <DeadlifeDust.stages.deadlife_dust-2.label>ölüyaşam tozu</DeadlifeDust.stages.deadlife_dust-2.label>
  <!-- EN: This dust stings! I can feel it in my eyes and lungs. -->
  <DeadlifeDust.stages.deadlife_dust-2.description>Bu toz batıyor! Onu gözlerimde ve ciğerlerimde hissediyorum.</DeadlifeDust.stages.deadlife_dust-2.description>
  
  <!-- EN: death pall -->
  <DeathPall.stages.death_pall.label>ölüm örtüsü</DeathPall.stages.death_pall.label>
  <!-- EN: It smells like death. -->
  <DeathPall.stages.death_pall.description>Ölüm gibi kokuyor.</DeathPall.stages.death_pall.description>
  <!-- EN: death pall exposure -->
  <DeathPall.stages.death_pall_exposure.label>ölüm örtüsüne maruz kalma</DeathPall.stages.death_pall_exposure.label>
  <!-- EN: It smells like death. My eyes sting and the air grits between my teeth. -->
  <DeathPall.stages.death_pall_exposure.description>Ölüm gibi kokuyor. Gözlerim acıyor ve hava dişlerimi gıcırdatıyor.</DeathPall.stages.death_pall_exposure.description>
  
  <!-- EN: death refusal -->
  <DeathRefusalSickness.stages.death_refusal.label>ölüm reddi</DeathRefusalSickness.stages.death_refusal.label>
  <!-- EN: I was dead… I died. It was cold and terrifying. -->
  <DeathRefusalSickness.stages.death_refusal.description>Ölüydüm... Öldüm. Soğuk ve dehşet vericiydi.</DeathRefusalSickness.stages.death_refusal.description>
  
  <!-- EN: my cube sculpture destroyed -->
  <DestroyedCubeSculpture.stages.my_cube_sculpture_destroyed.label>küp heykelim yok edildi</DestroyedCubeSculpture.stages.my_cube_sculpture_destroyed.label>
  <!-- EN: My sculpture... my beautiful sculpture... -->
  <DestroyedCubeSculpture.stages.my_cube_sculpture_destroyed.description>Heykelim... benim güzel heykelim...</DestroyedCubeSculpture.stages.my_cube_sculpture_destroyed.description>
  
  <!-- EN: monster by my bed -->
  <EntityInRoom.stages.monster_by_my_bed.label>yatağımın dibindeki canavar</EntityInRoom.stages.monster_by_my_bed.label>
  <!-- EN: I'll never be able to sleep with that twisted thing around! -->
  <EntityInRoom.stages.monster_by_my_bed.description>O iğrenç şey etraftayken asla uyuyamayacağım.</EntityInRoom.stages.monster_by_my_bed.description>
  
  <!-- EN: flesh tentacle -->
  <FleshTentacle.stages.flesh_tentacle.label>et dokunaç</FleshTentacle.stages.flesh_tentacle.label>
  <!-- EN: Get this thing off of me! -->
  <FleshTentacle.stages.flesh_tentacle.description>Beni şu şeyden kurtarın!</FleshTentacle.stages.flesh_tentacle.description>
  
  <!-- EN: flesh whip -->
  <FleshWhip.stages.flesh_whip.label>et kırbaç</FleshWhip.stages.flesh_whip.label>
  <!-- EN: It never stops squirming. I hate it. -->
  <FleshWhip.stages.flesh_whip.description>Sürekli kıvranıyor. Ondan nefret ediyorum.</FleshWhip.stages.flesh_whip.description>
  
  <!-- EN: gray pall -->
  <GrayPall.stages.gray_pall.label>gri örtü</GrayPall.stages.gray_pall.label>
  <!-- EN: It feels like the world is sick and dying. -->
  <GrayPall.stages.gray_pall.description>Dünya hastalanmış da ölüyormuş gibi hissediyorum.</GrayPall.stages.gray_pall.description>
  <!-- EN: gray pall exposure -->
  <GrayPall.stages.gray_pall_exposure.label>gri örtüye maruz kalma</GrayPall.stages.gray_pall_exposure.label>
  <!-- EN: It feels like the world is sick and dying. The putrid air makes me want to vomit. -->
  <GrayPall.stages.gray_pall_exposure.description>Dünya hastalanmış da ölüyormuş gibi hissediyorum. İğrenç hava yüzünden kusacakmış gibi oluyorum.</GrayPall.stages.gray_pall_exposure.description>
  
  <!-- EN: harbinger tree scream -->
  <HarbingerScream.stages.harbinger_tree_scream.label>alamet ağacı çığlığı</HarbingerScream.stages.harbinger_tree_scream.label>
  <!-- EN: I've had a pounding headache ever since that tree died. I can still hear it... -->
  <HarbingerScream.stages.harbinger_tree_scream.description>O ağaç öldüğünden beri kafam çatlayacakmış gibi ağrıyor. Onu hala duyabiliyorum...</HarbingerScream.stages.harbinger_tree_scream.description>
  
  <!-- EN: hate chant whispers -->
  <HateChantDrone.stages.hate_chant_whispers.label>nefret ilahisi fısıltıları</HateChantDrone.stages.hate_chant_whispers.label>
  <!-- EN: I hear their whispers, no matter where I am. Saying wrong things to me over and over. -->
  <HateChantDrone.stages.hate_chant_whispers.description>Nerede olursam olayım fısıltılarını duyuyorum. Bana devamlı korkunç şeyler söylüyor...</HateChantDrone.stages.hate_chant_whispers.description>
  <!-- EN: quiet hate chanting -->
  <HateChantDrone.stages.quiet_hate_chanting.label>sessiz nefret ilahisi</HateChantDrone.stages.quiet_hate_chanting.label>
  <!-- EN: I can hear them muttering, filling my mind with hatred, inside my head. -->
  <HateChantDrone.stages.quiet_hate_chanting.description>Kafamın içinde mırıldanmalarını duyabiliyorum, zihnimi nefretle dolduruyor.</HateChantDrone.stages.quiet_hate_chanting.description>
  <!-- EN: hate chanting -->
  <HateChantDrone.stages.hate_chanting.label>nefret ilahisi</HateChantDrone.stages.hate_chanting.label>
  <!-- EN: Those words being screamed into me, muttered, guttural moans of rage. Inside my head. It's driving me mad! -->
  <HateChantDrone.stages.hate_chanting.description>İçime işlenen o sözler, öfkenin boğuk sesi. Kafamın içinde. Beni deli ediyor!</HateChantDrone.stages.hate_chanting.description>
  <!-- EN: loud hate chanting -->
  <HateChantDrone.stages.loud_hate_chanting.label>yüksek sesli nefret ilahisi</HateChantDrone.stages.loud_hate_chanting.label>
  <!-- EN: The screaming doesn't stop, the chanting, inside me, in my head! -->
  <HateChantDrone.stages.loud_hate_chanting.description>Çığlıklar durmuyor, ilahi, içimde, kafamın içinde!</HateChantDrone.stages.loud_hate_chanting.description>
  <!-- EN: extreme hate chanting -->
  <HateChantDrone.stages.extreme_hate_chanting.label>gürültülü nefret ilahisi</HateChantDrone.stages.extreme_hate_chanting.label>
  <!-- EN: Rage in my head murderous rip the skin deserves it the black ocean terror deep... -->
  <HateChantDrone.stages.extreme_hate_chanting.description>Kafamdaki öfke, kanlı, deriyi parçala, hak ediyor, kara okyanus, dehşet, derinler...</HateChantDrone.stages.extreme_hate_chanting.description>
  
  <!-- EN: imprisoned with entity -->
  <ImprisonedWithEntity.stages.imprisoned_with_entity.label>varlıkla kapalı kaldı</ImprisonedWithEntity.stages.imprisoned_with_entity.label>
  <!-- EN: I'm trapped in here with that twisted thing! -->
  <ImprisonedWithEntity.stages.imprisoned_with_entity.description>Şu iğrenç şeyle burada kısılı kaldım!</ImprisonedWithEntity.stages.imprisoned_with_entity.description>
  
  <!-- EN: Joyous presence -->
  <JoyousPresence.stages.Joyous_presence.label>neşelinin mevcudiyeti</JoyousPresence.stages.Joyous_presence.label>
  <!-- EN: Wherever I go, I can feel the joyous one in the back of my mind. It makes me feel good. Very good. -->
  <JoyousPresence.stages.Joyous_presence.description>Nereye gidersem gideyim neşeli olanı ensemde hissedebiliyorum. Bu bana iyi hissettiriyor. Çok iyi.</JoyousPresence.stages.Joyous_presence.description>
  
  <!-- EN: juggernaut serum -->
  <JuggernautSerum.stages.juggernaut_serum.label>juggernaut serumu</JuggernautSerum.stages.juggernaut_serum.label>
  <!-- EN: This stuff messes with my head. I can't stop thinking the worst things. -->
  <JuggernautSerum.stages.juggernaut_serum.description>Bu şey kafamı bozuyor. En kötüsünü düşünmekten kendimi alıkoyamıyorum.</JuggernautSerum.stages.juggernaut_serum.description>
  
  <!-- EN: neurosis pulse -->
  <NeurosisPulse.stages.neurosis_pulse.label>nevrotik titreşim</NeurosisPulse.stages.neurosis_pulse.label>
  <!-- EN: Leave me alone! I have work to do! -->
  <NeurosisPulse.stages.neurosis_pulse.description>Beni yalnız bırak! Yapacak işlerim var!</NeurosisPulse.stages.neurosis_pulse.description>
  
  <!-- EN: pleasure pulse -->
  <PleasurePulse.stages.pleasure_pulse.label>keyif titreşimi</PleasurePulse.stages.pleasure_pulse.label>
  <!-- EN: My body ripples with joy. The world is a soft and fuzzy place. -->
  <PleasurePulse.stages.pleasure_pulse.description>Bedenim keyifle titriyor. Dünya yumuşak ve tüy gibi bir yer.</PleasurePulse.stages.pleasure_pulse.description>
  
  <!-- EN: Fascinating tome -->
  <ReadingTome.stages.Fascinating_tome.label>Büyüleyici kitap</ReadingTome.stages.Fascinating_tome.label>
  <!-- EN: Its almost as if it's speaking out to me personally. -->
  <ReadingTome.stages.Fascinating_tome.description>Sanki bizzat bana hitap ediyor gibi.</ReadingTome.stages.Fascinating_tome.description>
  
  <!-- EN: Sleep suppressor -->
  <SleepSuppressor.stages.Sleep_suppressor.label>Uyku baskılayıcı</SleepSuppressor.stages.Sleep_suppressor.label>
  <!-- EN: The hum of that devilish device grates. I feel it inside my head. What an evil piece of machinery. -->
  <SleepSuppressor.stages.Sleep_suppressor.description>O zalim cihazın uğultusu kulaklarımda çınlıyor. Onu kafamın içinde hissediyorum. Ne şeytani bir makine.</SleepSuppressor.stages.Sleep_suppressor.description>
  
  <!-- EN: unsettling conversation -->
  <SpokeToDisturbingMood.stages.unsettling_conversation.label>rahatsız edici sohbet</SpokeToDisturbingMood.stages.unsettling_conversation.label>
  <!-- EN: An unsettling conversation made me very creeped out. Nobody should think or speak of such things. -->
  <SpokeToDisturbingMood.stages.unsettling_conversation.description>Rahatsız edici bir sohbet tüylerimi diken diken etti. Hiç kimse böyle şeyleri düşünüp sözünü etmemeli.</SpokeToDisturbingMood.stages.unsettling_conversation.description>
  
  <!-- EN: swallowed by darkness -->
  <SwallowedByDarkness.stages.swallowed_by_darkness.label>karanlık tarafından yutulmuş</SwallowedByDarkness.stages.swallowed_by_darkness.label>
  <!-- EN: The darkness is suffocating. I can't see or think! -->
  <SwallowedByDarkness.stages.swallowed_by_darkness.description>Karanlık boğucu. Ne görebiliyorum ne düşünebiliyorum!</SwallowedByDarkness.stages.swallowed_by_darkness.description>
  
  <!-- EN: unnatural corpse -->
  <UnnaturalCorpse.stages.unnatural_corpse.label>anormal ceset</UnnaturalCorpse.stages.unnatural_corpse.label>
  <!-- EN: Wherever I go, I can feel it watching me. It never stops. -->
  <UnnaturalCorpse.stages.unnatural_corpse.description>Nereye gidersem gideyim beni izlediğini hissediyorum. Asla durmuyor.</UnnaturalCorpse.stages.unnatural_corpse.description>
  
  <!-- EN: unnatural darkness -->
  <UnnaturalDarkness.stages.unnatural_darkness.label>anormal karanlık</UnnaturalDarkness.stages.unnatural_darkness.label>
  <!-- EN: I am suffocated under a blanket of darkness. -->
  <UnnaturalDarkness.stages.unnatural_darkness.description>Karanlık örtüsünde boğuluyorum.</UnnaturalDarkness.stages.unnatural_darkness.description>
  <!-- EN: unnatural sky -->
  <UnnaturalDarkness.stages.unnatural_sky.label>anormal gökyüzü</UnnaturalDarkness.stages.unnatural_sky.label>
  <!-- EN: The truth finally comes and swallows this false world. -->
  <UnnaturalDarkness.stages.unnatural_sky.description>Hakikat sonunda gelip bu yanlış dünyayı yutuyor.</UnnaturalDarkness.stages.unnatural_sky.description>
  
  <!-- EN: captured entity -->
  <VoidFascination.stages.captured_entity.label>varlık yakalandı</VoidFascination.stages.captured_entity.label>
  <!-- EN: Such a magnificent creature. So much mystery. So much power. -->
  <VoidFascination.stages.captured_entity.description>Ne muhteşem bir varlık. Çok gizemli. Çok güçlü.</VoidFascination.stages.captured_entity.description>
  
  <!-- EN: void pleasure -->
  <VoidPleasure.stages.void_pleasure.label>hiçlik keyfi</VoidPleasure.stages.void_pleasure.label>
  <!-- EN: The vibrations of reality pulse into me and soothe everything. -->
  <VoidPleasure.stages.void_pleasure.description>Gerçekliğin titreşimleri içime doluyor ve her şeyi yumuşatıyor.</VoidPleasure.stages.void_pleasure.description>
  
  <!-- EN: voidsight -->
  <Voidsight.stages.voidsight.label>hiçlik görüsü</Voidsight.stages.voidsight.label>
  <!-- EN: The serum makes me see so much more. Connections everywhere, emotions flowing. Faces in the shadows. So much... -->
  <Voidsight.stages.voidsight.description>Serum çok daha fazlasını görmemi sağlıyor. Bağlantılar her yerde, duygular akıyor. Gölgelerdeki yüzler. Çok fazla...</Voidsight.stages.voidsight.description>
  
  <!-- EN: dread leather {0} -->
  <WearingDreadLeather.stages.dread_leather.label>ürkütücü deri {0}</WearingDreadLeather.stages.dread_leather.label>
  <!-- EN: I hate this stuff. It stinks. -->
  <WearingDreadLeather.stages.dread_leather.description>Bu şeyden nefret ediyorum. Çok kötü kokuyor.</WearingDreadLeather.stages.dread_leather.description>
  <!-- EN: dread leather {0} (+1) -->
  <WearingDreadLeather.stages.dread_leather_1.label>ürkütücü deri {0} (+1)</WearingDreadLeather.stages.dread_leather_1.label>
  <!-- EN: Two dread leather items. These make me uncomfortable. -->
  <WearingDreadLeather.stages.dread_leather_1.description>İki ürkütücü deriden eşya. Bu beni çok rahatsız ediyor.</WearingDreadLeather.stages.dread_leather_1.description>
  <!-- EN: dread leather {0} (+2) -->
  <WearingDreadLeather.stages.dread_leather_2.label>ürkütücü deri {0} (+2)</WearingDreadLeather.stages.dread_leather_2.label>
  <!-- EN: These three dread leather items make me squirm. They smell awful. -->
  <WearingDreadLeather.stages.dread_leather_2.description>Bu üç ürkütücü deriden eşya yüzünden içim çekiliyor. Berbat kokuyorlar.</WearingDreadLeather.stages.dread_leather_2.description>
  <!-- EN: dread leather {0} etc -->
  <WearingDreadLeather.stages.dread_leather_etc.label>ürkütücü deri {0} vb.</WearingDreadLeather.stages.dread_leather_etc.label>
  <!-- EN: I'm covered in this horrible stuff. -->
  <WearingDreadLeather.stages.dread_leather_etc.description>Bu korkunç şeyle kaplıyım.</WearingDreadLeather.stages.dread_leather_etc.description>
  
</LanguageData>