<?xml version="1.0" encoding="UTF-8"?>
<LanguageData>
  
  <!-- EN: blood torch -->
  <BloodTorch.stages.blood_torch.label>kan meşalesi</BloodTorch.stages.blood_torch.label>
  <!-- EN: No flame burns as softly as a blood torch. -->
  <BloodTorch.stages.blood_torch.description>Hiçbir alev, bir kan meşalesi kadar yumuşak yanmaz.</BloodTorch.stages.blood_torch.description>
  
  <!-- EN: childlike joy -->
  <ChildlikePositivity.stages.childlike_joy.label>çocuksu sevinç</ChildlikePositivity.stages.childlike_joy.label>
  <!-- EN: New! Fun! Pretty! Oooh! -->
  <ChildlikePositivity.stages.childlike_joy.description>Yeni! Eğlence! Tatlı! Oooh!</ChildlikePositivity.stages.childlike_joy.description>
  <!-- EN: childlike wonder -->
  <ChildlikePositivity.stages.childlike_wonder.label>çocuksu merak</ChildlikePositivity.stages.childlike_wonder.label>
  <!-- EN: The world is a magical place and I can't wait to grow up! -->
  <ChildlikePositivity.stages.childlike_wonder.description>Dünya büyülü bir yer ve büyümek için sabırsızlanıyorum!</ChildlikePositivity.stages.childlike_wonder.description>
  <!-- EN: childlike enthusiasm -->
  <ChildlikePositivity.stages.childlike_enthusiasm.label>çocuksu heves</ChildlikePositivity.stages.childlike_enthusiasm.label>
  <!-- EN: The world is full of wonders. -->
  <ChildlikePositivity.stages.childlike_enthusiasm.description>Dünya harikalarla dolu.</ChildlikePositivity.stages.childlike_enthusiasm.description>
  <!-- EN: childlike confidence -->
  <ChildlikePositivity.stages.childlike_confidence.label>çocuksu güven</ChildlikePositivity.stages.childlike_confidence.label>
  <!-- EN: There are so many interesting things to learn. -->
  <ChildlikePositivity.stages.childlike_confidence.description>Öğrenecek çok ilginç şeyler var.</ChildlikePositivity.stages.childlike_confidence.description>
  
  <!-- EN: deathrested outside -->
  <DeathrestChamber.stages.deathrested_outside.label>dışarıda ölüm uykusu</DeathrestChamber.stages.deathrested_outside.label>
  <!-- EN: I had to deathrest outdoors. It was awful. -->
  <DeathrestChamber.stages.deathrested_outside.description>Ölüm uykusuna dışarıda yatmak zorunda kaldım. Berbattı.</DeathrestChamber.stages.deathrested_outside.description>
  <!-- EN: awful deathrest chamber -->
  <DeathrestChamber.stages.awful_deathrest_chamber.label>berbat ölüm uykusu odası</DeathrestChamber.stages.awful_deathrest_chamber.label>
  <!-- EN: I had to deathrest in an awful chamber. -->
  <DeathrestChamber.stages.awful_deathrest_chamber.description>Berbat bir odada ölüm uykusuna yatmak zorunda kaldım.</DeathrestChamber.stages.awful_deathrest_chamber.description>
  <!-- EN: decent deathrest chamber -->
  <DeathrestChamber.stages.decent_deathrest_chamber.label>düzgün ölüm uykusu odası</DeathrestChamber.stages.decent_deathrest_chamber.label>
  <!-- EN: I deathrested in a decent chamber. -->
  <DeathrestChamber.stages.decent_deathrest_chamber.description>Düzgün bir odada ölüm uykusuna yattım.</DeathrestChamber.stages.decent_deathrest_chamber.description>
  <!-- EN: good deathrest chamber -->
  <DeathrestChamber.stages.good_deathrest_chamber.label>iyi ölüm uykusu odası</DeathrestChamber.stages.good_deathrest_chamber.label>
  <!-- EN: I deathrested in a slightly impressive chamber. It was nice. -->
  <DeathrestChamber.stages.good_deathrest_chamber.description>Biraz etkileyici bir odada ölüm uykusuna yattım. Güzeldi.</DeathrestChamber.stages.good_deathrest_chamber.description>
  <!-- EN: great deathrest chamber -->
  <DeathrestChamber.stages.great_deathrest_chamber.label>güzel ölüm uykusu odası</DeathrestChamber.stages.great_deathrest_chamber.label>
  <!-- EN: I deathrested in an impressive chamber. I feel rejuvenated. -->
  <DeathrestChamber.stages.great_deathrest_chamber.description>Etkileyici bir odada ölüm uykusuna yattım. Kendimi gençleşmiş hissediyorum.</DeathrestChamber.stages.great_deathrest_chamber.description>
  <!-- EN: excellent deathrest chamber -->
  <DeathrestChamber.stages.excellent_deathrest_chamber.label>mükemmel ölüm uykusu odası</DeathrestChamber.stages.excellent_deathrest_chamber.label>
  <!-- EN: I deathrested in a very impressive chamber. I feel amazing. -->
  <DeathrestChamber.stages.excellent_deathrest_chamber.description>Çok etkileyici bir odada ölüm uykusuna yattım. Harika hissediyorum.</DeathrestChamber.stages.excellent_deathrest_chamber.description>
  <!-- EN: exceptional deathrest chamber -->
  <DeathrestChamber.stages.exceptional_deathrest_chamber.label>olağanüstü ölüm uykusu odası</DeathrestChamber.stages.exceptional_deathrest_chamber.label>
  <!-- EN: I deathrested in an extremely impressive chamber. It was glorious. -->
  <DeathrestChamber.stages.exceptional_deathrest_chamber.description>Aşırı etkileyici bir odada ölüm uykusuna yattım. Muhteşemdi.</DeathrestChamber.stages.exceptional_deathrest_chamber.description>
  <!-- EN: unbelievable deathrest chamber -->
  <DeathrestChamber.stages.unbelievable_deathrest_chamber.label>inanılmaz ölüm uykusu odası</DeathrestChamber.stages.unbelievable_deathrest_chamber.label>
  <!-- EN: I deathrested in an unbelievably impressive chamber. It was spectacular. -->
  <DeathrestChamber.stages.unbelievable_deathrest_chamber.description>İnanılmaz derecede etkileyici bir odada ölüm uykusuna yattım. Çarpıcıydı.</DeathrestChamber.stages.unbelievable_deathrest_chamber.description>
  <!-- EN: wondrous deathrest chamber -->
  <DeathrestChamber.stages.wondrous_deathrest_chamber.label>harikulade ölüm uykusu odası</DeathrestChamber.stages.wondrous_deathrest_chamber.label>
  <!-- EN: I deathrested in such a luxurious chamber! It was wondrous. -->
  <DeathrestChamber.stages.wondrous_deathrest_chamber.description>Acayip şatafatlı bir odada ölüm uykusuna yattım. Harikuladeydi.</DeathrestChamber.stages.wondrous_deathrest_chamber.description>
  
  <!-- EN: deathrest exhaustion -->
  <DeathrestExhaustion.stages.deathrest_exhaustion.label>ölüm uykusu bitkinliği</DeathrestExhaustion.stages.deathrest_exhaustion.label>
  <!-- EN: The casket calls and I fall weary. The world's pall makes all so dreary. I need to deathrest. -->
  <DeathrestExhaustion.stages.deathrest_exhaustion.description>Tabut çağırıyor ve yorgun düşüyorum. Dünyanın hüznü her şeyi kasvetli kılıyor. Ölüm uykusuna ihtiyacım var.</DeathrestExhaustion.stages.deathrest_exhaustion.description>
  
  <!-- EN: genetic chemical dependency -->
  <GeneticChemicalDependency.stages.genetic_chemical_dependency.label>genetik kimyasal bağımlılığı</GeneticChemicalDependency.stages.genetic_chemical_dependency.label>
  <!-- EN: I need {CHEMICAL_label} because of my genetic deficiency. But it's been so long since I've had any. -->
  <GeneticChemicalDependency.stages.genetic_chemical_dependency.description>Genetik kusurum nedeniyle {CHEMICAL_label} almam lazım. Almayalı çok uzun zaman oldu.</GeneticChemicalDependency.stages.genetic_chemical_dependency.description>
  
  <!-- EN: apocriton hatred (intense) -->
  <HateAura.stages.apocriton_hatred_intense.label>apokriton nefreti (yoğun)</HateAura.stages.apocriton_hatred_intense.label>
  <!-- EN: I feel its hatred inside me, the way I feel my own emotions. It's so close and so cold. They all deserve death. -->
  <HateAura.stages.apocriton_hatred_intense.description>Onun nefretini içimde hissediyorum, kendi duygularımı hissettiğim gibi. Çok yakın ve çok soğuk. Hepsi ölümü hak ediyor.</HateAura.stages.apocriton_hatred_intense.description>
  <!-- EN: apocriton hatred (strong) -->
  <HateAura.stages.apocriton_hatred_strong.label>apokriton nefreti (güçlü)</HateAura.stages.apocriton_hatred_strong.label>
  <!-- EN: I hear its hatred echoing between my thoughts. Reasons, always reasons why my friends ought to die. -->
  <HateAura.stages.apocriton_hatred_strong.description>Düşüncelerim arasında yankılanan nefretini duyuyorum. Sebepler, her zaman arkadaşlarımın ölmesi için sebepler.</HateAura.stages.apocriton_hatred_strong.description>
  <!-- EN: apocriton hatred (distant) -->
  <HateAura.stages.apocriton_hatred_distant.label>apokriton nefreti (uzak)</HateAura.stages.apocriton_hatred_distant.label>
  <!-- EN: I feel it out there somewhere. It's always thinking about why these people deserve death. Always following the logic of murder. Hard to ignore. -->
  <HateAura.stages.apocriton_hatred_distant.description>Bir yerlerde onu hissediyorum. Daima bu insanların neden ölümü hak ettiğini düşünüyor. Daima cinayetin peşinden gidiyor. Görmezden gelmek zor.</HateAura.stages.apocriton_hatred_distant.description>
  
  <!-- EN: hemogen craving -->
  <HemogenCraving.stages.hemogen_craving-0.label>hemojen krizi</HemogenCraving.stages.hemogen_craving-0.label>
  <!-- EN: My bones ache. I really need hemogen. -->
  <HemogenCraving.stages.hemogen_craving-0.description>Kemiklerim ağrıyor. Gerçekten hemojene ihtiyacım var.</HemogenCraving.stages.hemogen_craving-0.description>
  <!-- EN: hemogen craving -->
  <HemogenCraving.stages.hemogen_craving-1.label>hemojen krizi</HemogenCraving.stages.hemogen_craving-1.label>
  <!-- EN: This hurts bad and my head is fuzzy. I would kill for some blood. Maybe I should. -->
  <HemogenCraving.stages.hemogen_craving-1.description>Canım çok yanıyor ve kafam bulanık. Biraz kan için can bile alırdım. Belki de yapmalıyım.</HemogenCraving.stages.hemogen_craving-1.description>
  <!-- EN: hemogen craving -->
  <HemogenCraving.stages.hemogen_craving-2.label>hemojen krizi</HemogenCraving.stages.hemogen_craving-2.label>
  <!-- EN: Can't think. Thirst. Thirst. Must. Have. Blood. -->
  <HemogenCraving.stages.hemogen_craving-2.description>Düşünemiyorum. Susuzluk. Susuzluk. Zorundayım. Almalıyım. Kan.</HemogenCraving.stages.hemogen_craving-2.description>
  
  <!-- EN: kill thirst -->
  <KillThirst.stages.kill_thirst.label>kana susama</KillThirst.stages.kill_thirst.label>
  <!-- EN: Must kill... it has been too long since I have killed somebody up close and personal. -->
  <KillThirst.stages.kill_thirst.description>Öldürmeliyim... yakından ve birebirde birini öldürmeyeli çok uzun zaman oldu.</KillThirst.stages.kill_thirst.description>
  
  <!-- EN: acidic smog -->
  <NoxiousHaze.stages.acidic_smog.label>asidik sis</NoxiousHaze.stages.acidic_smog.label>
  <!-- EN: The smog makes my eyes water and it smells awful. I wish I could just have a few fresh breaths. -->
  <NoxiousHaze.stages.acidic_smog.description>Sis gözlerimi sulandırıyor ve çok kötü kokuyor. Keşke biraz temiz hava alabilseydim.</NoxiousHaze.stages.acidic_smog.description>
  
  <!-- EN: new pregnancy -->
  <PregnancyAttitude.stages.new_pregnancy-0.label>hamile kaldım</PregnancyAttitude.stages.new_pregnancy-0.label>
  <!-- EN: I'm pregnant! It makes me happy. -->
  <PregnancyAttitude.stages.new_pregnancy-0.description>Hamileyim! Bu durum beni mutlu ediyor.</PregnancyAttitude.stages.new_pregnancy-0.description>
  <!-- EN: new pregnancy -->
  <PregnancyAttitude.stages.new_pregnancy-1.label>hamile kaldım</PregnancyAttitude.stages.new_pregnancy-1.label>
  <!-- EN: I'm pregnant and not very happy about it. -->
  <PregnancyAttitude.stages.new_pregnancy-1.description>Hamileyim ve bundan pek memnun değilim.</PregnancyAttitude.stages.new_pregnancy-1.description>
  
  <!-- EN: collapse -->
  <PregnancyMood_Collapse.labelInBracketsExtraForHediff>çöküş</PregnancyMood_Collapse.labelInBracketsExtraForHediff>
  <!-- EN: pregnancy mood collapse -->
  <PregnancyMood_Collapse.stages.pregnancy_mood_collapse.label>hamilelik ruh hâli çöküşü</PregnancyMood_Collapse.stages.pregnancy_mood_collapse.label>
  <!-- EN: This pregnancy is so hard. My body always feels awful. So exhausting! -->
  <PregnancyMood_Collapse.stages.pregnancy_mood_collapse.description>Hamilelik çok zor. Bedenim daima berbat hissediyor. Çok yorucu!</PregnancyMood_Collapse.stages.pregnancy_mood_collapse.description>
  
  <!-- EN: down -->
  <PregnancyMood_Down.labelInBracketsExtraForHediff>düşüş</PregnancyMood_Down.labelInBracketsExtraForHediff>
  <!-- EN: pregnancy mood down -->
  <PregnancyMood_Down.stages.pregnancy_mood_down.label>hamilelik ruh hâli düşüşü</PregnancyMood_Down.stages.pregnancy_mood_down.label>
  <!-- EN: It feels like everything is going wrong for me today. Pregnancy is tough. -->
  <PregnancyMood_Down.stages.pregnancy_mood_down.description>Bugün her işim ters gidiyor gibi geliyor. Hamilelik zor.</PregnancyMood_Down.stages.pregnancy_mood_down.description>
  
  <!-- EN: high -->
  <PregnancyMood_High.labelInBracketsExtraForHediff>artış</PregnancyMood_High.labelInBracketsExtraForHediff>
  <!-- EN: pregnancy mood high -->
  <PregnancyMood_High.stages.pregnancy_mood_high.label>hamilelik ruh hâli artışı</PregnancyMood_High.stages.pregnancy_mood_high.label>
  <!-- EN: I feel amazing! Being pregnant is a gift! -->
  <PregnancyMood_High.stages.pregnancy_mood_high.description>Harika hissediyorum! Hamile olmak bir lütuf!</PregnancyMood_High.stages.pregnancy_mood_high.description>
  
  <!-- EN: up -->
  <PregnancyMood_Up.labelInBracketsExtraForHediff>yüksek</PregnancyMood_Up.labelInBracketsExtraForHediff>
  <!-- EN: pregnancy mood up -->
  <PregnancyMood_Up.stages.pregnancy_mood_up.label>hamilelik ruh hâli yüksek</PregnancyMood_Up.stages.pregnancy_mood_up.label>
  <!-- EN: Everything feels a little bit more pleasant today. Pregnancy is nice. -->
  <PregnancyMood_Up.stages.pregnancy_mood_up.description>Bugün her şey biraz daha keyifli hissettiriyor. Hamilelik güzel.</PregnancyMood_Up.stages.pregnancy_mood_up.description>
  
  <!-- EN: psychic bond -->
  <PsychicBondProximity.stages.psychic_bond.label>psişik bağ</PsychicBondProximity.stages.psychic_bond.label>
  <!-- EN: The bond brings us together, sharing feelings and thoughts. It's like a friend who is always with me. -->
  <PsychicBondProximity.stages.psychic_bond.description>Bağ, duygu ve düşüncelerimizi paylaştırarak bizi bir araya getiriyor. Daima yanımda olan bir arkadaş gibi.</PsychicBondProximity.stages.psychic_bond.description>
  <!-- EN: psychic bond distance -->
  <PsychicBondProximity.stages.psychic_bond_distance.label>psişik bağ mesafesi</PsychicBondProximity.stages.psychic_bond_distance.label>
  <!-- EN: The distance makes it so hard to hear. I feel alone, like standing in a dark, silent cavern. -->
  <PsychicBondProximity.stages.psychic_bond_distance.description>Mesafe, duymayı çok zorlaştırıyor. Karanlık, sessiz bir mağarada duruyormuş gibi yalnız hissediyorum.</PsychicBondProximity.stages.psychic_bond_distance.description>
  
  <!-- EN: recluse alone -->
  <Recluse.stages.recluse_alone.label>yalnız münzevi</Recluse.stages.recluse_alone.label>
  <!-- EN: It's a relief not to have to think about other people. -->
  <Recluse.stages.recluse_alone.description>Başkalarını düşünmek zorunda kalmamak rahatlatıcı.</Recluse.stages.recluse_alone.description>
  <!-- EN: recluse in small group -->
  <Recluse.stages.recluse_in_small_group.label>küçük gruptaki münzevi</Recluse.stages.recluse_in_small_group.label>
  <!-- EN: I'm happy I don't have too many people to think about. Alone would be better, but this is good too. -->
  <Recluse.stages.recluse_in_small_group.description>Düşünecek çok fazla insan olmadığı için mutluyum. Tek başıma olsam daha iyi olurdu ama bu da iyi.</Recluse.stages.recluse_in_small_group.description>
  <!-- EN: recluse crowded -->
  <Recluse.stages.recluse_crowded.label>kalabalıktaki münzevi</Recluse.stages.recluse_crowded.label>
  <!-- EN: There's too many people around here. The weight of having to think about them bears down on me. -->
  <Recluse.stages.recluse_crowded.description>Etrafta çok fazla insan var. Onları düşünmek zorunda olmanın ağırlığı üzerime çöküyor.</Recluse.stages.recluse_crowded.description>
  <!-- EN: recluse very crowded -->
  <Recluse.stages.recluse_very_crowded.label>çok kalabalıktaki münzevi</Recluse.stages.recluse_very_crowded.label>
  <!-- EN: There are so many people I'm supposed to be working with. They're overwhelming. -->
  <Recluse.stages.recluse_very_crowded.description>Birlikte çalışmam gereken çok insan var. Boğucular.</Recluse.stages.recluse_very_crowded.description>
  
  <!-- EN: scanning sickness -->
  <ScanningSickness.stages.scanning_sickness.label>tarama hastalığı</ScanningSickness.stages.scanning_sickness.label>
  <!-- EN: Ever since that scan I've been dizzy and I can't think. -->
  <ScanningSickness.stages.scanning_sickness.description>O taramadan beri başım dönüyor ve düşünemiyorum.</ScanningSickness.stages.scanning_sickness.description>
  
  <!-- EN: sunlight sensitivity -->
  <SunlightSensitivity_Major.stages.sunlight_sensitivity.label>güneş ışığı hassasiyeti</SunlightSensitivity_Major.stages.sunlight_sensitivity.label>
  <!-- EN: The sunlight burns my eyes and my skin feels like it's being scorched. -->
  <SunlightSensitivity_Major.stages.sunlight_sensitivity.description>Güneş ışığı gözlerimi yakıyor ve cildim kavruluyor gibi hissediyorum.</SunlightSensitivity_Major.stages.sunlight_sensitivity.description>
  
  <!-- EN: sunlight sensitivity -->
  <SunlightSensitivity_Mild.stages.sunlight_sensitivity.label>güneş ışığı hassasiyeti</SunlightSensitivity_Mild.stages.sunlight_sensitivity.label>
  <!-- EN: The sun hurts my eyes and my skin is tingling unpleasantly. -->
  <SunlightSensitivity_Mild.stages.sunlight_sensitivity.description>Güneş gözlerimi acıtıyor ve cildim rahatsız edici biçimde karıncalanıyor.</SunlightSensitivity_Mild.stages.sunlight_sensitivity.description>
  
</LanguageData>