<?xml version="1.0" encoding="UTF-8"?>
<LanguageData>
  
  <!-- EN: imperial laborer -->
  <Empire_Common_Laborer.label>imparatorluk işçisi</Empire_Common_Laborer.label>
  <Empire_Common_Laborer.labelFemale>imparatorluk işçisi</Empire_Common_Laborer.labelFemale>
  <Empire_Common_Laborer.labelPlural>imparatorluk işçileri</Empire_Common_Laborer.labelPlural>
  
  <!-- EN: imperial citizen -->
  <Empire_Common_Lodger.label>imparatorluk vatandaşı</Empire_Common_Lodger.label>
  <Empire_Common_Lodger.labelFemale>imparatorluk vatandaşı</Empire_Common_Lodger.labelFemale>
  <Empire_Common_Lodger.labelPlural>imparatorluk vatandaşları</Empire_Common_Lodger.labelPlural>
  
  <!-- EN: imperial trader -->
  <Empire_Common_Trader.label>imparatorluk tüccarı</Empire_Common_Trader.label>
  <Empire_Common_Trader.labelFemale>imparatorluk tüccarı</Empire_Common_Trader.labelFemale>
  <Empire_Common_Trader.labelPlural>imparatorluk tüccarları</Empire_Common_Trader.labelPlural>
  
  <!-- EN: cataphract -->
  <Empire_Fighter_Cataphract.label>katafrakt</Empire_Fighter_Cataphract.label>
  <Empire_Fighter_Cataphract.labelPlural>katafraktlar</Empire_Fighter_Cataphract.labelPlural>
  
  <!-- EN: champion -->
  <Empire_Fighter_Champion.label>şampiyon</Empire_Fighter_Champion.label>
  <Empire_Fighter_Champion.labelFemale>şampiyon</Empire_Fighter_Champion.labelFemale>
  <Empire_Fighter_Champion.labelPlural>şampiyonlar</Empire_Fighter_Champion.labelPlural>
  
  <!-- EN: imperial grenadier -->
  <Empire_Fighter_Grenadier.label>imparatorluk bombacısı</Empire_Fighter_Grenadier.label>
  <Empire_Fighter_Grenadier.labelFemale>imparatorluk bombacısı</Empire_Fighter_Grenadier.labelFemale>
  <Empire_Fighter_Grenadier.labelPlural>imparatorluk bombacıları</Empire_Fighter_Grenadier.labelPlural>
  
  <!-- EN: janissary -->
  <Empire_Fighter_Janissary.label>yeniçeri</Empire_Fighter_Janissary.label>
  <Empire_Fighter_Janissary.labelPlural>yeniçeriler</Empire_Fighter_Janissary.labelPlural>
  
  <!-- EN: stellic warden -->
  <Empire_Fighter_StellicGuardMelee.label>yıldız gardiyanı</Empire_Fighter_StellicGuardMelee.label>
  <Empire_Fighter_StellicGuardMelee.labelFemale>yıldız gardiyanı</Empire_Fighter_StellicGuardMelee.labelFemale>
  <Empire_Fighter_StellicGuardMelee.labelPlural>yıldız gardiyanları</Empire_Fighter_StellicGuardMelee.labelPlural>
  
  <!-- EN: stellic defender -->
  <Empire_Fighter_StellicGuardRanged.label>yıldız muhafızı</Empire_Fighter_StellicGuardRanged.label>
  <Empire_Fighter_StellicGuardRanged.labelFemale>yıldız muhafızı</Empire_Fighter_StellicGuardRanged.labelFemale>
  <Empire_Fighter_StellicGuardRanged.labelPlural>yıldız muhafızları</Empire_Fighter_StellicGuardRanged.labelPlural>
  
  <!-- EN: trooper -->
  <Empire_Fighter_Trooper.label>asker</Empire_Fighter_Trooper.label>
  <Empire_Fighter_Trooper.labelPlural>askerler</Empire_Fighter_Trooper.labelPlural>
  
  <!-- EN: acolyte -->
  <Empire_Royal_Acolyte.label>mürit</Empire_Royal_Acolyte.label>
  <Empire_Royal_Acolyte.labelFemale>mürit</Empire_Royal_Acolyte.labelFemale>
  
  <!-- EN: baron -->
  <Empire_Royal_Baron.label>baron</Empire_Royal_Baron.label>
  <!-- EN: baroness -->
  <Empire_Royal_Baron.labelFemale>barones</Empire_Royal_Baron.labelFemale>
  
  <!-- EN: bestower -->
  <Empire_Royal_Bestower.label>bahşeden</Empire_Royal_Bestower.label>
  <Empire_Royal_Bestower.labelFemale>bahşeden</Empire_Royal_Bestower.labelFemale>
  
  <!-- EN: consul -->
  <Empire_Royal_Consul.label>konsül</Empire_Royal_Consul.label>
  <Empire_Royal_Consul.labelFemale>konsül</Empire_Royal_Consul.labelFemale>
  
  <!-- EN: count -->
  <Empire_Royal_Count.label>kont</Empire_Royal_Count.label>
  <!-- EN: countess -->
  <Empire_Royal_Count.labelFemale>kontes</Empire_Royal_Count.labelFemale>
  
  <!-- EN: duke -->
  <Empire_Royal_Duke.label>dük</Empire_Royal_Duke.label>
  <!-- EN: duchess -->
  <Empire_Royal_Duke.labelFemale>düşes</Empire_Royal_Duke.labelFemale>
  
  <!-- EN: knight -->
  <Empire_Royal_Knight.label>şövalye</Empire_Royal_Knight.label>
  <!-- EN: dame -->
  <Empire_Royal_Knight.labelFemale>şövalye</Empire_Royal_Knight.labelFemale>
  
  <!-- EN: noble -->
  <Empire_Royal_NobleWimp.label>soylu</Empire_Royal_NobleWimp.label>
  <Empire_Royal_NobleWimp.labelFemale>soylu</Empire_Royal_NobleWimp.labelFemale>
  
  <!-- EN: praetor -->
  <Empire_Royal_Praetor.label>praetor</Empire_Royal_Praetor.label>
  <Empire_Royal_Praetor.labelFemale>praetor</Empire_Royal_Praetor.labelFemale>
  
  <!-- EN: stellarch -->
  <Empire_Royal_Stellarch.label>yıldız lordu</Empire_Royal_Stellarch.label>
  
  <!-- EN: yeoman -->
  <Empire_Royal_Yeoman.label>yaver</Empire_Royal_Yeoman.label>
  <Empire_Royal_Yeoman.labelFemale>yaver</Empire_Royal_Yeoman.labelFemale>
  
  <!-- EN: slave -->
  <Slave_Empire.label>köle</Slave_Empire.label>
  
</LanguageData>