<?xml version="1.0" encoding="UTF-8"?>
<LanguageData>
  
  <!-- EN: gravship range -->
  <GravshipRange.label>gravgemi menzili</GravshipRange.label>
  <!-- EN: The maximum distance this gravship can travel with its connected substructure. -->
  <GravshipRange.description>Bu gravgeminin bağlı altyapısıyla seyahat edebileceği maksimum mesafeyi belirler.</GravshipRange.description>
  
  <!-- EN: substructure support -->
  <SubstructureSupport.label>altyapı desteği</SubstructureSupport.label>
  <!-- EN: The maximum amount of substructure supported by this gravship. -->
  <SubstructureSupport.description>Bu gravgeminin desteklediği maksimum altyapı miktarını belirler.</SubstructureSupport.description>
  
</LanguageData>