<?xml version="1.0" encoding="UTF-8"?>
<LanguageData>
  
  <!-- EN: centipede blaster -->
  <Mech_CentipedeBlaster.label>kırkayak</Mech_CentipedeBlaster.label>
  <!-- EN: Heavy combat mechanoids that glide on dozens of tiny legs. Their thick carapace and firepower makes them very effective against bunched-up static defenders. They are somewhat vulnerable to mobile hit-and-run tactics. -->
  <Mech_CentipedeBlaster.description>Düzinelerce küçük bacak üzerinde kayan ağır savaş mekanoidleri. Ağır zırhları ve ateş güçleri, onları bir araya toplanmış statik savunuculara karşı çok etkili kılar. Mobil vur-kaç taktiklerine karşı biraz savunmasızdırlar.</Mech_CentipedeBlaster.description>
  <!-- EN: head -->
  <Mech_CentipedeBlaster.tools.head.label>kafa</Mech_CentipedeBlaster.tools.head.label>
  
  <!-- EN: centipede burner -->
  <Mech_CentipedeBurner.label>kırkayak brülörü</Mech_CentipedeBurner.label>
  <!-- EN: Heavy combat mechanoids that glide on dozens of tiny legs. Their thick carapace and firepower makes them very effective against bunched-up static defenders. They are somewhat vulnerable to mobile hit-and-run tactics. -->
  <Mech_CentipedeBurner.description>Düzinelerce küçük bacak üzerinde kayan ağır savaş mekanoidleri. Kalın kabukları ve ateş güçleri, onları bir araya toplanmış statik savunuculara karşı çok etkili kılar. Mobil vur-kaç taktiklerine karşı biraz savunmasızdırlar.</Mech_CentipedeBurner.description>
  <!-- EN: head -->
  <Mech_CentipedeBurner.tools.head.label>Kafa</Mech_CentipedeBurner.tools.head.label>
  
  <!-- EN: centipede gunner -->
  <Mech_CentipedeGunner.label>kırkayak topçusu</Mech_CentipedeGunner.label>
  <!-- EN: Heavy combat mechanoids that glide on dozens of tiny legs. Their thick carapace and firepower makes them very effective against bunched-up static defenders. They are somewhat vulnerable to mobile hit-and-run tactics. -->
  <Mech_CentipedeGunner.description>Düzinelerce küçük bacak üzerinde kayan ağır savaş mekanoidleri. Kalın kabukları ve ateş güçleri, onları bir araya toplanmış statik savunuculara karşı çok etkili kılar. Mobil vur-kaç taktiklerine karşı biraz savunmasızdırlar.</Mech_CentipedeGunner.description>
  <!-- EN: head -->
  <Mech_CentipedeGunner.tools.head.label>Kafa</Mech_CentipedeGunner.tools.head.label>
  
  <!-- EN: lancer -->
  <Mech_Lancer.label>lancer</Mech_Lancer.label>
  <!-- EN: Fast human-sized combat mechanoids built for medium and long-range combat. Their bodies are light, making them vulnerable targets at close range - especially in melee combat. -->
  <Mech_Lancer.description>Orta ve uzun menzilli savaş için inşa edilmiş hızlı, insan boyutunda savaş mekanoidleri. Vücutları hafiftir, bu da onları yakın mesafeden - özellikle yakın dövüşte - savunmasız hedefler haline getirir.</Mech_Lancer.description>
  <!-- EN: left fist -->
  <Mech_Lancer.tools.left_fist.label>sol yumruk</Mech_Lancer.tools.left_fist.label>
  <!-- EN: right fist -->
  <Mech_Lancer.tools.right_fist.label>sağ yumruk</Mech_Lancer.tools.right_fist.label>
  <!-- EN: head -->
  <Mech_Lancer.tools.head.label>kafa</Mech_Lancer.tools.head.label>
  
  <!-- EN: pikeman -->
  <Mech_Pikeman.label>mızraklı</Mech_Pikeman.label>
  <!-- EN: A clunky multi-legged combat mechanoid specialized as a long-range weapons platform. While effective at distance, it is weak in close-range fights and in melee combat.\n\nVeterans of mechanoid wars know that often, the safest place to be around a pikeman is touching it. -->
  <Mech_Pikeman.description>Uzun menzilli bir silah platformu olarak uzmanlaşmış, tıknaz, çok bacaklı bir savaş mekanoidi. Uzaktan etkili olsa da, yakın mesafeli dövüşlerde ve yakın dövüşte zayıftır.\n\nMekanoid savaşların gazileri bilir ki, genellikle bir mızrakçının etrafında olmak için en güvenli yer ona dokunmaktır.</Mech_Pikeman.description>
  <!-- EN: front left leg -->
  <Mech_Pikeman.tools.front_left_leg.label>ön sol bacak</Mech_Pikeman.tools.front_left_leg.label>
  <!-- EN: front right leg -->
  <Mech_Pikeman.tools.front_right_leg.label>ön sağ bacak</Mech_Pikeman.tools.front_right_leg.label>
  <!-- EN: head -->
  <Mech_Pikeman.tools.head.label>kafa</Mech_Pikeman.tools.head.label>
  
  <!-- EN: scyther -->
  <Mech_Scyther.label>tırpanlı</Mech_Scyther.label>
  <!-- EN: Fast, spindly, human-sized combat mechanoids specializing in rapid approach and close-range combat. Their bodies are covered in points and blades, but they mostly use their two arm blades to lop off limbs or gut their victims alive. -->
  <Mech_Scyther.description>Hızlı, cılız, insan boyutunda savaş mekanoidleri. Genellikle bir birincil menzilli silah taşırlar ve vücutları, onları yakın muharebede ölümcül kılmak için iki eklemli bıçakla süslenmiştir. Kılıf kullanmazlar. En iyi konsantre, ezici güç tarafından ele alınır.</Mech_Scyther.description>
  <!-- EN: left blade -->
  <Mech_Scyther.tools.left_blade.label>sol bıçak</Mech_Scyther.tools.left_blade.label>
  <!-- EN: right blade -->
  <Mech_Scyther.tools.right_blade.label>sağ bıçak</Mech_Scyther.tools.right_blade.label>
  <!-- EN: head -->
  <Mech_Scyther.tools.head.label>kafa</Mech_Scyther.tools.head.label>
  
  <!-- EN: termite -->
  <Mech_Termite.label>termit</Mech_Termite.label>
  <!-- EN: A medium-sized mechanoid. Termites specialize in burrowing, digging, and breaking through defensive structures. Defenders need to decide whether to try to eliminate the termite before it can dig through their defenses, or take it where it emerges. -->
  <Mech_Termite.description>Orta büyüklükte bir mekanoid. Termitler, savunma yapılarını oyuk açma, kazma ve kırma konusunda uzmanlaşmıştır. Savunucuların, termiti savunmalarını kazmadan önce ortadan kaldırmaya mı yoksa ortaya çıktığı yere mi götürmeye karar vermeleri gerekiyor.</Mech_Termite.description>
  <!-- EN: head -->
  <Mech_Termite.tools.head.label>kafa</Mech_Termite.tools.head.label>
  
</LanguageData>