<?xml version="1.0" encoding="UTF-8"?>
<LanguageData>
  
  <!-- EN: alphabeaver -->
  <Alphabeaver.label>alfa kunduz</Alphabeaver.label>
  <Alphabeaver.labelPlural>alfa kunduzlar</Alphabeaver.labelPlural>
  <Alphabeaver.lifeStages.0.label>alfa kunduz yavrusu</Alphabeaver.lifeStages.0.label>
  <Alphabeaver.lifeStages.0.labelPlural>alfa kunduz yavruları</Alphabeaver.lifeStages.0.labelPlural>
  
  <!-- EN: cobra -->
  <Cobra.label>Kobra</Cobra.label>
  <Cobra.labelPlural>Kobralar</Cobra.labelPlural>
  <Cobra.lifeStages.0.label>Kobra yavrusu</Cobra.lifeStages.0.label>
  <Cobra.lifeStages.0.labelPlural>Kobra yavruları</Cobra.lifeStages.0.labelPlural>
  
  <!-- EN: thrumbo -->
  <Thrumbo.label>Thrumbo</Thrumbo.label>
  <Thrumbo.labelPlural>Thrumbolar</Thrumbo.labelPlural>
  <!-- EN: thrumbo calf -->
  <Thrumbo.lifeStages.thrumbo_calf.label>Thrumbo yavrusu</Thrumbo.lifeStages.thrumbo_calf.label>
  <!-- EN: thrumbo calves -->
  <Thrumbo.lifeStages.thrumbo_calf.labelPlural>Thrumbo yavruları</Thrumbo.lifeStages.thrumbo_calf.labelPlural>
  
  <!-- EN: tortoise -->
  <Tortoise.label>tosbağa</Tortoise.label>
  <Tortoise.labelPlural>tosbağalar</Tortoise.labelPlural>
  <Tortoise.lifeStages.0.label>tosbağa yavrusu</Tortoise.lifeStages.0.label>
  <Tortoise.lifeStages.0.labelPlural>tosbağa yavruları</Tortoise.lifeStages.0.labelPlural>
  
</LanguageData>