<?xml version="1.0" encoding="UTF-8"?>
<LanguageData>
  
  <!-- EN: alpaca -->
  <Alpaca.label>alpaka</Alpaca.label>
  <Alpaca.labelPlural>alpakalar</Alpaca.labelPlural>
  <Alpaca.lifeStages.0.label>yavru alpaka</Alpaca.lifeStages.0.label>
  <Alpaca.lifeStages.0.labelPlural>yavru alpakalar</Alpaca.lifeStages.0.labelPlural>
  
  <!-- EN: capybara -->
  <Capybara.label>kapibara</Capybara.label>
  <Capybara.labelPlural>kapibaralar</Capybara.labelPlural>
  <Capybara.lifeStages.0.label>yavru kapibara</Capybara.lifeStages.0.label>
  <Capybara.lifeStages.0.labelPlural>yavru kapibaralar</Capybara.lifeStages.0.labelPlural>
  
  <!-- EN: megasloth -->
  <Megasloth.label>dev miskin</Megasloth.label>
  <Megasloth.labelPlural>dev miskinler</Megasloth.labelPlural>
  <Megasloth.lifeStages.0.label>dev miskin yavrusu</Megasloth.lifeStages.0.label>
  <Megasloth.lifeStages.0.labelPlural>dev miskin yavruları</Megasloth.lifeStages.0.labelPlural>
  
  <!-- EN: sheep -->
  <Sheep.label>koyun</Sheep.label>
  <!-- EN: ewe -->
  <Sheep.labelFemale>koyun</Sheep.labelFemale>
  <Sheep.labelFemalePlural>koyunlar</Sheep.labelFemalePlural>
  <!-- EN: ram -->
  <Sheep.labelMale>koç</Sheep.labelMale>
  <Sheep.labelMalePlural>koçlar</Sheep.labelMalePlural>
  <!-- EN: sheep -->
  <Sheep.labelPlural>koyunlar</Sheep.labelPlural>
  <!-- EN: lamb -->
  <Sheep.lifeStages.lamb.label>kuzu</Sheep.lifeStages.lamb.label>
  <!-- EN: lambs -->
  <Sheep.lifeStages.lamb.labelPlural>kuzular</Sheep.lifeStages.lamb.labelPlural>
  
</LanguageData>