<?xml version="1.0" encoding="utf-8" ?>
<LanguageData>
    
	<NamerFactionSpacer.rulePack.rulesStrings>
		<li>name->Kosmonauta</li>
	</NamerFactionSpacer.rulePack.rulesStrings>
    
	<NamerFactionPirate.rulePack.rulesStrings>
		<li>name->the [badassanimal]s</li>
		<li>name->the [badassanimal] men</li>
		<li>name->the [badassanimal]s of [badassconcept]</li>
		<li>name->the [badassperson]s of [badassconcept]</li>
		<li>name->the [badassperson]s</li>
		<li>name->the [weapon] Men</li>
		<li>name->the [weapon]s</li>
		<li>name->the [weapon] [badassanimal]</li>
		<li>name->the [badasscolor] [weapon]</li>
		<li>name->the [badasscolor] [badassanimal]</li>
		<li>name->the [badasscolor] [badassperson]</li>
		<li>name->the [badassperson] [groupname]</li>
		<li>name->the [badassadjective] [groupname]</li>
		<li>name->the [badassadjective] [badassanimal]</li>
		<li>name->the [badassadjective] [badassperson]</li>
		<li>name->[weapon] [groupname]</li>
		<li>name->[badassconcept] [groupname]</li>
		<li>name->[badassconcept] [groupname]</li>
		<li>name->[badassanimal]s [terrainfeature]</li>
	</NamerFactionPirate.rulePack.rulesStrings>
    
	<NamerColony.rulePack.rulesStrings>
		<li>name->[colonyname]</li>
	</NamerColony.rulePack.rulesStrings>
    
	<NamerFactionOutlander.rulePack.rulesStrings>
		<li>rule->[positiveconcept]'s [terrainfeature]</li>
		<li>rule->[outlander]'s [terrainfeature]</li>
		<li>rule->[outlander]'s [community]</li>
		<li>rule->[community]-at-The-[terrainfeature]</li>
	</NamerFactionOutlander.rulePack.rulesStrings>
    
	<NamerFactionTribal.rulePack.rulesStrings>
		<li>name->[tribalword] [tribalword]</li>
		<li>name->[tribalword] [tribalword]</li>
		<li>name->[tribalword] [tribalword] [tribalword]</li>
		<li>name->[tribalword] of [animal]</li>
		<li>name->[color] [animal] [tribalword]</li>
		<li>name->[tribalword] of the [terrainfeature]</li>
		<li>name->[color] [terrainfeature] People</li>
	</NamerFactionTribal.rulePack.rulesStrings>
    
</LanguageData>