<?xml version="1.0" encoding="UTF-8"?>
<LanguageData>

  <!-- EN: d -->
  <LetterDay>G</LetterDay>
  <!-- EN: h -->
  <LetterHour>S</LetterHour>
  <!-- EN: m -->
  <LetterMinute>D</LetterMinute>
  <!-- EN: s -->
  <LetterSecond>s</LetterSecond>
  <!-- EN: y -->
  <LetterYear>Y</LetterYear>

  <!-- EN: days -->
  <DaysLower>Günler</DaysLower>
  <!-- EN: hours -->
  <HoursLower>saatler</HoursLower>
  <!-- EN: seconds -->
  <SecondsLower>saniyeler</SecondsLower>

  <!-- EN: spring -->
  <SeasonSpring>ilkbahar</SeasonSpring>
  <!-- EN: summer -->
  <SeasonSummer>yaz</SeasonSummer>
  <!-- EN: fall -->
  <SeasonFall>sonbahar</SeasonFall>
  <!-- EN: winter -->
  <SeasonWinter>kış</SeasonWinter>
  <!-- EN: permanent summer -->
  <SeasonPermanentSummer>kalıcı yaz</SeasonPermanentSummer>
  <!-- EN: permanent winter -->
  <SeasonPermanentWinter>kalıcı kış</SeasonPermanentWinter>

  <!-- EN: Aprimay -->
  <QuadrumAprimay>Nisan</QuadrumAprimay>
  <!-- EN: Jugust -->
  <QuadrumJugust>Ağustos</QuadrumJugust>
  <!-- EN: Septober -->
  <QuadrumSeptober>Eylül</QuadrumSeptober>
  <!-- EN: Decembary -->
  <QuadrumDecembary>Aralık</QuadrumDecembary>

  <!-- EN: Apr -->
  <QuadrumAprimay_Short>Nis</QuadrumAprimay_Short>
  <!-- EN: Jug -->
  <QuadrumJugust_Short>Ağs</QuadrumJugust_Short>
  <!-- EN: Sep -->
  <QuadrumSeptober_Short>Eyl</QuadrumSeptober_Short>
  <!-- EN: Dec -->
  <QuadrumDecembary_Short>Ara</QuadrumDecembary_Short>
  
  <!-- EN: Born: {0} -->
  <Born>Born: {0}</Born>
  <!-- EN: Chronological age: {0} years, {1} quadrums, {2} days -->
  <AgeChronological>Kronolojik yaş: {0} yıl, {1} ay, {2} gün</AgeChronological>
  <!-- EN: Biological age: {0} years, {1} quadrums, {2} days -->
  <AgeBiological>Biyolojik yaþ: {0} yıl, {1} ay, {2} gün</AgeBiological>

  <!-- Date periods -->
  <!-- EN: 1 year -->
  <Period1Year>yıl</Period1Year>
  <!-- EN: {0} years -->
  <PeriodYears>{0} yıl</PeriodYears>
  <!-- EN: 1 quadrum -->
  <Period1Quadrum>1 yıl</Period1Quadrum>
  <!-- EN: {0} quadrums -->
  <PeriodQuadrums>{0} yıllar</PeriodQuadrums>
  <!-- EN: 1 day -->
  <Period1Day>1 gün</Period1Day>
  <!-- EN: {0} days -->
  <PeriodDays>{0} günler</PeriodDays>
  <!-- EN: 1 hour -->
  <Period1Hour>1 saat</Period1Hour>
  <!-- EN: {0} hours -->
  <PeriodHours>{0} saatler</PeriodHours>
  <!-- EN: 1 second -->
  <Period1Second>1 saniye</Period1Second>
  <!-- EN: {0} seconds -->
  <PeriodSeconds>{0} saniyeler</PeriodSeconds>

  <!-- Misc -->
  <!-- EN: Started -->
  <Started>Başladı</Started>
  <!-- EN: Lasted -->
  <Lasted>Sürdü</Lasted>
  <!-- EN: occurred {0} ago -->
  <OccurredTimeAgo>{0} önce oldu</OccurredTimeAgo>
  
</LanguageData>