<?xml version="1.0" encoding="UTF-8"?>
<LanguageData>
  
  <!-- EN: animals -->
  <Animals.label>hayvanlar</Animals.label>
  <!-- EN: Configure how the colony's tame animals should be treated. -->
  <Animals.description>Kolonindeki evcil hayvanların nasıl davranacağını yapılandır.</Animals.description>
  
  <!-- EN: architect -->
  <Architect.label>mimari</Architect.label>
  <!-- EN: Designate where to build, farm, store items, and so on. -->
  <Architect.description>Nerede inşa, ekim, depolama yapacağını vb. tanımla.</Architect.description>
  
  <!-- EN: assign -->
  <Assign.label>atama</Assign.label>
  <!-- EN: Assign behaviors to colonists like what they should wear, what drugs to take, or how to respond to enemies. -->
  <Assign.description>Kolonistlerinin davranışlarını, giyimlerini, hangi uyuşturucuyu alacağını vb. ata.</Assign.description>
  
  <!-- EN: factions -->
  <Factions.label>fraksiyonlar</Factions.label>
  <!-- EN: Review the other factions on this world and their relationships. -->
  <Factions.description>Dünyadaki diğer fraksiyonlar ve ilişkilerini görüntüle.</Factions.description>
  
  <!-- EN: history -->
  <History.label>tarih</History.label>
  <!-- EN: Review historical records. -->
  <History.description>Tarihsel kayıtları görüntüle.</History.description>
  
  <!-- EN: inspect -->
  <Inspect.label>inceleme</Inspect.label>
  
  <!-- EN: menu -->
  <Menu.label>menü</Menu.label>
  <!-- EN: Change options, save, load, or quit the game. -->
  <Menu.description>Ayarları değiştir, oyunu kaydet, yükle veya çık.</Menu.description>
  
  <!-- EN: quests -->
  <Quests.label>görevler</Quests.label>
  <!-- EN: View available, active, and historical quests. -->
  <Quests.description>Mevcut, etkin ve eski görevleri görüntüle.</Quests.description>
  
  <!-- EN: research -->
  <Research.label>araştırma</Research.label>
  <!-- EN: Examine and decide on research projects. -->
  <Research.description>Araştırma projelerini incele ve karar ver.</Research.description>
  
  <!-- EN: schedule -->
  <Schedule.label>program</Schedule.label>
  <!-- EN: Schedule colonists' activities to certain times of day, and set their allowed areas. -->
  <Schedule.description>Kolonistleri günün belirli saatlerinde belirli etkinliklerle veya belirli izin verilen alanlarla sınırla.</Schedule.description>
  
  <!-- EN: wildlife -->
  <Wildlife.label>yaban</Wildlife.label>
  <!-- EN: List wild animals in the area and designate them for hunting or taming. -->
  <Wildlife.description>Bölgedeki listelenmiş hayvanları avlamak veya evcilleştirmek için işaretle.</Wildlife.description>
  
  <!-- EN: work -->
  <Work.label>iş</Work.label>
  <!-- EN: Choose which colonist does what kinds of work, and in what order. -->
  <Work.description>Hangi kolonistin hangi işleri hangi sırayla yapacağını seç.</Work.description>
  
  <!-- EN: world -->
  <World.label>dünya</World.label>
  <!-- EN: Examine the world map, form, and manage caravans. -->
  <World.description>Dünya haritasını incele ve kervan oluştur.</World.description>
  
</LanguageData>